metaflow/R.py
metaflow/__init__.py
metaflow/cards.py
metaflow/cli.py
metaflow/cli_args.py
metaflow/cmd_with_io.py
metaflow/current.py
metaflow/debug.py
metaflow/decorators.py
metaflow/event_logger.py
metaflow/exception.py
metaflow/flowspec.py
metaflow/graph.py
metaflow/includefile.py
metaflow/lint.py
metaflow/main_cli.py
metaflow/metaflow_config.py
metaflow/metaflow_environment.py
metaflow/metaflow_profile.py
metaflow/metaflow_version.py
metaflow/monitor.py
metaflow/multicore_utils.py
metaflow/package.py
metaflow/parameters.py
metaflow/procpoll.py
metaflow/pylint_wrapper.py
metaflow/runtime.py
metaflow/sidecar.py
metaflow/sidecar_messages.py
metaflow/sidecar_worker.py
metaflow/task.py
metaflow/unbounded_foreach.py
metaflow/util.py
metaflow/client/__init__.py
metaflow/client/core.py
metaflow/client/filecache.py
metaflow/datastore/__init__.py
metaflow/datastore/content_addressed_store.py
metaflow/datastore/datastore_set.py
metaflow/datastore/datastore_storage.py
metaflow/datastore/exceptions.py
metaflow/datastore/flow_datastore.py
metaflow/datastore/inputs.py
metaflow/datastore/local_storage.py
metaflow/datastore/s3_storage.py
metaflow/datastore/task_datastore.py
metaflow/datatools/__init__.py
metaflow/datatools/s3.py
metaflow/datatools/s3op.py
metaflow/datatools/s3tail.py
metaflow/datatools/s3util.py
metaflow/metadata/__init__.py
metaflow/metadata/heartbeat.py
metaflow/metadata/metadata.py
metaflow/metadata/util.py
metaflow/mflog/__init__.py
metaflow/mflog/mflog.py
metaflow/mflog/redirect_streams.py
metaflow/mflog/save_logs.py
metaflow/mflog/save_logs_periodically.py
metaflow/mflog/tee.py
metaflow/plugins/__init__.py
metaflow/plugins/catch_decorator.py
metaflow/plugins/debug_logger.py
metaflow/plugins/debug_monitor.py
metaflow/plugins/environment_decorator.py
metaflow/plugins/package_cli.py
metaflow/plugins/parallel_decorator.py
metaflow/plugins/project_decorator.py
metaflow/plugins/resources_decorator.py
metaflow/plugins/retry_decorator.py
aero_metaflow-2.5.dist-info/LICENSE
aero_metaflow-2.5.dist-info/METADATA
aero_metaflow-2.5.dist-info/WHEEL
aero_metaflow-2.5.dist-info/entry_points.txt
aero_metaflow-2.5.dist-info/top_level.txt
aero_metaflow-2.5.dist-info/RECORD
