Metadata-Version: 2.1
Name: aero-metaflow
Version: 2.5
Summary: Aero fork of Metaflow
Author: Aero
Author-email: aero@robbiea.co.uk
License: Apache License 2.0
Platform: UNKNOWN
License-File: LICENSE
Requires-Dist: click (>=7.0)
Requires-Dist: requests
Requires-Dist: boto3
Requires-Dist: pylint (<2.5.0)
Requires-Dist: inquirer
